calc/__init__.py
calc/calculator.py
tests/__init__.py
tests/test_Basics.py
CalculatorPackageDTTT-1.0.dist-info/LICENSE
CalculatorPackageDTTT-1.0.dist-info/METADATA
CalculatorPackageDTTT-1.0.dist-info/WHEEL
CalculatorPackageDTTT-1.0.dist-info/top_level.txt
CalculatorPackageDTTT-1.0.dist-info/RECORD
